[
    {
        "image": "https://img23.melmod.com/2024/12/old-dragon-fruit.webp",
        "zipUrl": "https://d3.melmod.com/mods/Olddragonfruit.zip",
        "title": "old dragon fruit",
        "description": "old dragon fruit in Melon Playground",
        "stars": "5",
        "ratingNum": "5",
        "itemNumDownload": "1",
        "itemNumViews": "1",
        "itemSize": "2.1 Mb"
    },
    {
        "image": "https://img23.melmod.com/2024/09/dragon-fruit.webp",
        "zipUrl": "https://d3.melmod.com/mods/dragonfruitmod.zip",
        "title": "dragon fruit",
        "description": "dragon fruit in Melon Playground Mod",
        "stars": "5",
        "ratingNum": "5",
        "itemNumDownload": "1",
        "itemNumViews": "1",
        "itemSize": "2.09 Mb"
    },
     {
        "image": "https://img23.melmod.com/2024/05/Yellow-Light-Fruit-Impostor-.webp",
        "zipUrl": "https://d3.melmod.com/mods/LightYellowImpostor.zip",
        "title": "Yellow Light Fruit & Impostor ",
        "description": "Yellow Light Fruit & Impostor  in Melon Playground Mod",
        "stars": "5",
        "ratingNum": "5",
        "itemNumDownload": "1",
        "itemNumViews": "1",
        "itemSize": "1.46 Mb"
    },
     {
        "image": "https://img23.melmod.com/2023/10/more-fruits.webp",
        "zipUrl": "https://d3.melmod.com/mods/morefruits2.zip",
        "title": "more fruits",
        "description": "Avocado, Banana, Banana Fruit, Blueberry, Blueberry Fruit, Cacus, Carrot, Carrot Vegetable, Cherry, Cherry Fruit, Chilli Vegetable, Coconut, Coconut Ball, Dark grape, Dragon Fruit, Dragonfruit, Egg, Eggplant, Eggplant Vegetable, Grape, Grapefruit, Green grape, Jelly, Kiwi, Lemon, Lemon Fruit, Mango, Mushroom, Mushroom Fungus, Onion, Onion Vegetable, Pea, Peach, Pear, Peas, Pickle, Pickle Vegetable, Pineapple, Pineapple Fruit, Pomegranate, Potato, Raspberry, Squash, Strawberry, Strawberry Fruit, Tomato, Tomato Vegetable",
        "stars": "5",
        "ratingNum": "5",
        "itemNumDownload": "1",
        "itemNumViews": "1",
        "itemSize": "1.1 Mb"
    },
     {
        "image": "https://img23.melmod.com/2024/02/Blox-Fruits-Wave-IV5.webp",
        "zipUrl": "https://d3.melmod.com/mods/BloxFruits.zip",
        "title": "Blox Fruits",
        "description": "Blox Fruits Melon Playground Mod",
        "stars": "5",
        "ratingNum": "5",
        "itemNumDownload": "1",
        "itemNumViews": "1",
        "itemSize": "1.06 Mb" 
    },
     {
        "image": "https://img23.melmod.com/2023/06/fruits-and-vegetables.jpg",
        "zipUrl": "https://d3.melmod.com/mods/fruitsandvegetables.zip",
        "title": "fruits and vegetables",
        "description": "fruits and vegetables",
        "stars": "5",
        "ratingNum": "5",
        "itemNumDownload": "1",
        "itemNumViews": "1",
        "itemSize": "12.3 Mb"
    }
]
